randbyrand.py
randbyrand-1.1.0.dist-info/LICENSE.txt
randbyrand-1.1.0.dist-info/METADATA
randbyrand-1.1.0.dist-info/WHEEL
randbyrand-1.1.0.dist-info/top_level.txt
randbyrand-1.1.0.dist-info/RECORD
