Metadata-Version: 2.1
Name: randbyrand
Version: 1.1.0
Summary: Retrive a million random digits by RAND Corporation.
Home-page: https://github.com/lucafrance/randbyrand
Author: Luca Franceschini
Author-email: luca.france@outlook.com
License: MIT License
Platform: UNKNOWN
Classifier: Programming Language :: Python :: 3
Classifier: License :: OSI Approved :: MIT License
Classifier: Operating System :: OS Independent
Requires-Python: >=3.8
Requires-Dist: requests
Requires-Dist: numpy
Requires-Dist: pandas
